fontMath/__init__.py
fontMath/_version.py
fontMath/mathFunctions.py
fontMath/mathGlyph.py
fontMath/mathGuideline.py
fontMath/mathInfo.py
fontMath/mathKerning.py
fontMath/mathTransform.py
fontMath/test/__init__.py
fontMath/test/test_mathFunctions.py
fontMath/test/test_mathGlyph.py
fontMath/test/test_mathGuideline.py
fontMath/test/test_mathInfo.py
fontMath/test/test_mathKerning.py
fontMath/test/test_mathTransform.py
fontMath-0.9.3.dist-info/License.txt
fontMath-0.9.3.dist-info/METADATA
fontMath-0.9.3.dist-info/WHEEL
fontMath-0.9.3.dist-info/top_level.txt
fontMath-0.9.3.dist-info/zip-safe
fontMath-0.9.3.dist-info/RECORD
