Metadata-Version: 2.1
Name: fontMath
Version: 0.9.3
Summary: A set of objects for performing math operations on font data.
Home-page: https://github.com/robotools/fontMath
Author: Tal Leming
Author-email: tal@typesupply.com
License: MIT
Classifier: Development Status :: 4 - Beta
Classifier: Intended Audience :: Developers
Classifier: License :: OSI Approved :: MIT License
Classifier: Operating System :: OS Independent
Classifier: Programming Language :: Python
Classifier: Programming Language :: Python :: 2
Classifier: Programming Language :: Python :: 3
Classifier: Topic :: Multimedia :: Graphics :: Editors :: Vector-Based
Classifier: Topic :: Software Development :: Libraries :: Python Modules
Requires-Python: >=3.7
License-File: License.txt
